tests/__init__.py
tests/test_base.py
tests/test_data.py
tests/test_generic.py
tests/test_indicators.py
tests/test_labels.py
tests/test_portfolio.py
tests/test_records.py
tests/test_returns.py
tests/test_settings.py
tests/test_signals.py
tests/test_utils.py
tests/utils.py
vectorbt/__init__.py
vectorbt/_settings.py
vectorbt/_typing.py
vectorbt/_version.py
vectorbt/ohlcv_accessors.py
vectorbt/px_accessors.py
vectorbt/root_accessors.py
vectorbt/base/__init__.py
vectorbt/base/accessors.py
vectorbt/base/array_wrapper.py
vectorbt/base/column_grouper.py
vectorbt/base/combine_fns.py
vectorbt/base/index_fns.py
vectorbt/base/indexing.py
vectorbt/base/reshape_fns.py
vectorbt/data/__init__.py
vectorbt/data/base.py
vectorbt/data/custom.py
vectorbt/data/updater.py
vectorbt/generic/__init__.py
vectorbt/generic/accessors.py
vectorbt/generic/decorators.py
vectorbt/generic/drawdowns.py
vectorbt/generic/enums.py
vectorbt/generic/nb.py
vectorbt/generic/plots_builder.py
vectorbt/generic/plotting.py
vectorbt/generic/ranges.py
vectorbt/generic/splitters.py
vectorbt/generic/stats_builder.py
vectorbt/indicators/__init__.py
vectorbt/indicators/basic.py
vectorbt/indicators/configs.py
vectorbt/indicators/factory.py
vectorbt/indicators/nb.py
vectorbt/labels/__init__.py
vectorbt/labels/enums.py
vectorbt/labels/generators.py
vectorbt/labels/nb.py
vectorbt/messaging/__init__.py
vectorbt/messaging/telegram.py
vectorbt/portfolio/__init__.py
vectorbt/portfolio/base.py
vectorbt/portfolio/decorators.py
vectorbt/portfolio/enums.py
vectorbt/portfolio/logs.py
vectorbt/portfolio/nb.py
vectorbt/portfolio/orders.py
vectorbt/portfolio/trades.py
vectorbt/records/__init__.py
vectorbt/records/base.py
vectorbt/records/col_mapper.py
vectorbt/records/decorators.py
vectorbt/records/mapped_array.py
vectorbt/records/nb.py
vectorbt/returns/__init__.py
vectorbt/returns/accessors.py
vectorbt/returns/metrics.py
vectorbt/returns/nb.py
vectorbt/returns/qs_adapter.py
vectorbt/signals/__init__.py
vectorbt/signals/accessors.py
vectorbt-0.27.0.dist-info/LICENSE.md
vectorbt-0.27.0.dist-info/METADATA
vectorbt-0.27.0.dist-info/WHEEL
vectorbt-0.27.0.dist-info/top_level.txt
vectorbt-0.27.0.dist-info/RECORD
