Metadata-Version: 2.1
Name: vectorbt
Version: 0.27.0
Summary: Python library for backtesting and analyzing trading strategies at scale
Home-page: https://github.com/polakowo/vectorbt
Author: Oleg Polakow
Author-email: olegpolakow@gmail.com
License: Apache 2.0 with Commons Clause
Classifier: Development Status :: 5 - Production/Stable
Classifier: Intended Audience :: Developers
Classifier: Intended Audience :: Financial and Insurance Industry
Classifier: License :: Free for non-commercial use
Classifier: Programming Language :: Python :: 3.6
Classifier: Programming Language :: Python :: 3.7
Classifier: Programming Language :: Python :: 3.8
Classifier: Programming Language :: Python :: 3.9
Classifier: Programming Language :: Python :: 3.10
Classifier: Programming Language :: Python :: 3.11
Classifier: Programming Language :: Python :: 3.12
Classifier: Operating System :: OS Independent
Classifier: Intended Audience :: Science/Research
Classifier: Topic :: Software Development
Classifier: Topic :: Office/Business :: Financial
Classifier: Topic :: Scientific/Engineering :: Information Analysis
Requires-Python: >=3.6
License-File: LICENSE.md
Requires-Dist: numpy>=1.16.5
Requires-Dist: pandas
Requires-Dist: scipy
Requires-Dist: matplotlib
Requires-Dist: plotly>=4.12.0
Requires-Dist: ipywidgets>=7.0.0
Requires-Dist: numba<0.57.0,>=0.53.1; python_version < "3.10"
Requires-Dist: numba<0.57.0,>=0.56.0; python_version >= "3.10" and python_version < "3.11"
Requires-Dist: numba>=0.57.0; python_version >= "3.11"
Requires-Dist: dill
Requires-Dist: tqdm
Requires-Dist: dateparser
Requires-Dist: imageio
Requires-Dist: scikit-learn
Requires-Dist: schedule
Requires-Dist: requests
Requires-Dist: pytz
Requires-Dist: typing_extensions; python_version < "3.8"
Requires-Dist: mypy_extensions
Provides-Extra: full
Requires-Dist: yfinance>=0.2.22; extra == "full"
Requires-Dist: python-binance; extra == "full"
Requires-Dist: ccxt>=4.0.14; extra == "full"
Requires-Dist: alpaca-py; extra == "full"
Requires-Dist: ray>=1.4.1; extra == "full"
Requires-Dist: ta; extra == "full"
Requires-Dist: pandas_ta; extra == "full"
Requires-Dist: TA-Lib; extra == "full"
Requires-Dist: python-telegram-bot<20.0,>=13.4; extra == "full"
Requires-Dist: quantstats>=0.0.37; extra == "full"
Provides-Extra: cov
Requires-Dist: pytest; extra == "cov"
Requires-Dist: pytest-cov; extra == "cov"
Requires-Dist: codecov; extra == "cov"
